setup.py
Scratch_Analysis_Tool/AntlrLexer.py
Scratch_Analysis_Tool/AntlrListener.py
Scratch_Analysis_Tool/AntlrParser.py
Scratch_Analysis_Tool/Gen.py
Scratch_Analysis_Tool/__init__.py
Scratch_Analysis_Tool.egg-info/PKG-INFO
Scratch_Analysis_Tool.egg-info/SOURCES.txt
Scratch_Analysis_Tool.egg-info/dependency_links.txt
Scratch_Analysis_Tool.egg-info/entry_points.txt
Scratch_Analysis_Tool.egg-info/requires.txt
Scratch_Analysis_Tool.egg-info/top_level.txt